flask_unsign/__init__.py
flask_unsign/__main__.py
flask_unsign/cracker.py
flask_unsign/exceptions.py
flask_unsign/helpers.py
flask_unsign/logger.py
flask_unsign/session.py
flask_unsign-1.0.0.dist-info/LICENSE.md
flask_unsign-1.0.0.dist-info/METADATA
flask_unsign-1.0.0.dist-info/WHEEL
flask_unsign-1.0.0.dist-info/entry_points.txt
flask_unsign-1.0.0.dist-info/top_level.txt
flask_unsign-1.0.0.dist-info/RECORD
