Metadata-Version: 2.1
Name: flask-unsign
Version: 1.0.0
Summary: Flask Unsign is a penetration testing utility that attempts to uncover a Flask server's secret key by taking a signed session verifying it against a wordlist of commonly used and publicly known secret keys (sourced from books, GitHub, StackOverflow and various other sources).
Home-page: https://github.com/Paradoxis/Flask-Unsign
Author: Luke Paris (Paradoxis)
Author-email: luke@paradoxis.nl
License: MIT
Platform: UNKNOWN
Classifier: License :: OSI Approved :: MIT License
Classifier: Programming Language :: Python
Classifier: Programming Language :: Python :: 3
Classifier: Programming Language :: Python :: 3.6
Classifier: Programming Language :: Python :: Implementation :: CPython
Classifier: Programming Language :: Python :: Implementation :: PyPy
Requires-Python: >=3.6.0
License-File: LICENSE.md
Requires-Dist: flask
Requires-Dist: requests
Requires-Dist: itsdangerous
Requires-Dist: markupsafe
Requires-Dist: werkzeug
Provides-Extra: dev
Requires-Dist: twine ; extra == 'dev'
Requires-Dist: wheel ; extra == 'dev'
Requires-Dist: setuptools (>=40.6.3) ; extra == 'dev'
Provides-Extra: test
Requires-Dist: coverage ; extra == 'test'
Requires-Dist: codecov ; extra == 'test'
Provides-Extra: wordlist
Requires-Dist: flask-unsign-wordlist ; extra == 'wordlist'
